supMath/__init__.py
supMath/supConverters.py
supMath/supGeometry.py
supMath/supOperators.py
supMath-0.5.1.2.dist-info/METADATA
supMath-0.5.1.2.dist-info/WHEEL
supMath-0.5.1.2.dist-info/top_level.txt
supMath-0.5.1.2.dist-info/RECORD
