Metadata-Version: 2.1
Name: supMath
Version: 0.5.1.2
Summary: Provides large amount of unique mathematical functions and operators
Author: landee
Author-email: ivankurd2007@gmail.com
Classifier: Programming Language :: Python :: 3.12
Classifier: License :: OSI Approved :: MIT License
Classifier: Operating System :: OS Independent
